COPYING
MANIFEST.in
README.md
setup.py
Djamo.egg-info/PKG-INFO
Djamo.egg-info/SOURCES.txt
Djamo.egg-info/dependency_links.txt
Djamo.egg-info/requires.txt
Djamo.egg-info/top_level.txt
djamo/__init__.py
djamo/base.py
djamo/cache.py
djamo/db.py
djamo/document.py
djamo/index.py
djamo/collections/__init__.py
djamo/collections/base.py
djamo/collections/collection.py
djamo/serializers/__init__.py
djamo/serializers/_django.py
djamo/serializers/_embedded.py
djamo/serializers/_list.py
djamo/serializers/_numeric.py
djamo/serializers/_string.py
djamo/serializers/base.py
djamo/utils/__init__.py
djamo/utils/six.py
docs/Makefile
docs/__init__.py
docs/mongo_extensions.py
docs/source/conf.py
docs/source/faq.rst
docs/source/index.rst
docs/source/installation.rst
docs/source/otherresources.rst
docs/source/quickstart.rst
tests/__init__.py
tests/main.py
tests/test_collection.py
tests/test_serializers.py