Metadata-Version: 1.1
Name: Djamo
Version: 2.67.0-rc2
Summary: Yet another Mongodb driver for Django
Home-page: http://djamo.yellowen.com/
Author: Sameer Rahmani
Author-email: lxsameer@gnu.org
License: GPL v2
Download-URL: http://djamo.yellowen.com/downloads/
Keywords: web development mongo
Platform: UNKNOWN
Classifier: Development Status :: 5 - Production/Stable
Classifier: Environment :: Console
Classifier: Intended Audience :: Developers
Classifier: License :: OSI Approved :: GNU General Public License (GPL)
Classifier: Operating System :: POSIX :: Linux
Classifier: Programming Language :: Python
Classifier: Topic :: Software Development :: Libraries :: Python Modules
Classifier: Topic :: Utilities
